{
  "checkpoints": {
    "vggt_baseline": "/home/zhw/lab_users/xyb/home/projects/vggt-human/checkpoints/vggt_omega_1b_512.pt",
    "yolo8x": "/home/zhw/lab_users/xyb/home/projects/vggt-human/checkpoints/yolov8x.torchscript",
    "nlf_smpl": "/home/zhw/lab_users/xyb/home/projects/vggt-human/third_party/weights/nlf/nlf_l_multi_0.3.2.torchscript",
    "sat_hmr_smpl": "/home/zhw/xyb_space/SAT-HMR/weights/sat_hmr/sat_644.pth"
  },
  "assets": {
    "smpl_model_dir": "/home/zhw/lab_users/xyb/home/projects/vggt-human/checkpoints/body_models/smpl",
    "smpl_mean_params": "/home/zhw/lab_users/xyb/home/projects/vggt-human/checkpoints/body_models/smpl/smpl/smpl_mean_params.npz"
  },
  "datasets": {
    "bedlam_root": "/home/zhw/xyb_space/bedlam/processed_bedlam",
    "bedlam_boxes_root": "/home/zhw/lab_users/xyb/home/projects/vggt-human/outputs/preprocess/bedlam_boxes",
    "bedlam_tracks_root": "outputs/preprocess/video_tracks",
    "hf_bedlam_images_root": "/home/zhw/xyb_space/bedlam/hf_bedlam/training_images",
    "hf_bedlam_npz_root": "/home/zhw/xyb_space/bedlam/all_npz_12_training",
    "hf_bedlam_sam2_patch_masks_root": "outputs/preprocess/hf_bedlam_sam2_patch_masks",
    "emdb_hmr4d_support_root": "/home/zhw/xyb_space/EMDB/hmr4d_support",
    "rich_hmr4d_support_root": "/home/zhw/xyb_space/RICH/hmr4d_support",
    "threedpw_hmr4d_support_root": "/home/zhw/xyb_space/3DPW/hmr4d_support",
    "threedpw_root": "/home/zhw/xyb_space/3DPW",
    "threedpw_smpl_base_root": "outputs/preprocess/3dpw_smpl_base",
    "threedpw_sam2_patch_masks_root": "outputs/preprocess/3dpw_sam2_patch_masks",
    "hmr4d_eval_frames_root": "outputs/preprocess/hmr4d_eval_frames",
    "hmr4d_eval_tracks_root": "outputs/preprocess/hmr4d_eval_tracks"
  },
  "third_party": {
    "boosttrack_root": "third_party/BoostTrack",
    "boosttrack_weights_root": "third_party/weights/BoostTrack",
    "sam2_root": "third_party/sam2",
    "sam2_checkpoint": "third_party/weights/sam/sam2.1_hiera_large.pt",
    "Omnieraser_root": "third_party/Omnieraser",
    "Omnieraser_checkpoint": "third_party/weights/Omnieraser/controlnet_flux_pytorch_lora_weights.safetensors",
    "nlf_root": "third_party/nlf"
  },
  "experiment": {
    "name": "hsi_stage2_v4_a1_correction",
    "output_dir": "/home/zhw/lab_users/xyb/home/projects/vggt-human/outputs/debug/hsi_stage2_v4_a1_overfit64_residual_gain_1000_20260718",
    "seed": 42
  },
  "data": {
    "dataset": "bedlam",
    "root_key": "datasets.bedlam_root",
    "train_split": "Training",
    "val_split": "Training",
    "sequence_length": 2,
    "stride": 1,
    "image_size": 518,
    "image_resolution": 512,
    "resize_mode": "balanced",
    "max_humans": 20,
    "boxes_root_key": "datasets.bedlam_boxes_root",
    "require_boxes": true,
    "require_smpl": true,
    "require_depth": true,
    "num_workers": 16,
    "pin_memory": true,
    "train_sequence_manifest": "/home/zhw/lab_users/xyb/home/projects/vggt-human/outputs/preprocess/hsi_sequence_split_v2/train_sequences.txt",
    "val_sequence_manifest": "/home/zhw/lab_users/xyb/home/projects/vggt-human/outputs/preprocess/hsi_sequence_split_v2/train_sequences.txt",
    "subset_indices_csv": "/home/zhw/lab_users/xyb/home/projects/vggt-human/outputs/preprocess/hsi_sequence_split_v2/overfit64_indices.csv",
    "subset_repeat": 400,
    "subset_max_samples": 0,
    "subset_apply_to_val": true
  },
  "model": {
    "patch_size": 16,
    "embed_dim": 1024,
    "enable_camera": true,
    "enable_depth": true,
    "enable_alignment": false,
    "enable_smpl": true,
    "enable_hsi_refine": true,
    "enable_hsi_human_scene_align": false,
    "enable_hsi_translation_refine_v4": true,
    "enable_hsi_contact_refine": false,
    "smpl_provider": "gt_perturbed",
    "num_smpl_queries": 20,
    "smpl_query_box_prior": true,
    "smpl_track_assignment_mode": "gt",
    "smpl_use_external_track_prior": false,
    "predict_boxes": false,
    "predict_id_embed": false,
    "smpl_return_aux": false,
    "freeze_aggregator": true,
    "freeze_aggregator_forward": true,
    "freeze_camera_head": true,
    "freeze_dense_head": true,
    "freeze_hsi_scene_affine": true,
    "freeze_hsi_backbone": true,
    "train_hsi_v4_correction_only": true,
    "hsi_scene_affine_mode": "clip_median",
    "hsi_enable_temporal_momentum": false,
    "hsi_v4_hidden_dim": 256,
    "hsi_v4_num_sample_vertices": 128,
    "hsi_v4_local_window": 7,
    "hsi_v4_min_correspondences": 12,
    "hsi_v4_max_ray_ratio": 0.25,
    "hsi_v4_ray_parameterization": "residual_gain",
    "hsi_v4_max_ray_gain": 4.0,
    "hsi_v4_max_tangent_delta_m": 0.12,
    "hsi_v4_max_correspondence_distance_m": 3.5,
    "hsi_v4_residual_mad_multiplier": 3.0,
    "hsi_v4_max_depth_m": 20.0,
    "hsi_v4_phase": "correction",
    "hsi_v4_gate_threshold": 0.5,
    "hsi_v4_overwrite_refined": true,
    "hsi_geometry_mode": "gt_metric"
  },
  "checkpoint": {
    "resume": "/home/zhw/lab_users/xyb/home/projects/vggt-human/outputs/train/stage1_scale_linear_b20_gpu7/checkpoint_top_train_epoch_0003_loss_total_0.171740.pt",
    "load_vggt_baseline": true,
    "strict": false,
    "resume_strict": false,
    "resume_optimizer": false,
    "resume_required_prefixes": "hsi_refinement_head.",
    "reset_epoch": true,
    "save_scope": "hsi",
    "save_prefixes": [
      "hsi_refinement_head.",
      "hsi_translation_refine_v4_head."
    ],
    "save_optimizer": false,
    "save_epoch_checkpoint": false,
    "save_latest": true,
    "save_final": false,
    "save_top_k": 3,
    "save_top_k_from_train": false,
    "topk_create_stable_copies": true,
    "monitor": "metric_hsi_v4_selection",
    "monitor_mode": "min",
    "frozen_hash_prefixes": "hsi_refinement_head."
  },
  "optim": {
    "batch_size": 24,
    "epochs": 1,
    "lr": 2e-05,
    "weight_decay": 0.05,
    "grad_clip_norm": 1.0,
    "log_interval": 20,
    "log_style": "progress",
    "progress_bar_width": 28,
    "progress_max_loss_items": 12,
    "progress_log_keys": "loss_total,loss_hsi_v4_candidate_transl,loss_hsi_v4_candidate_ray,loss_hsi_v4_candidate_tangent,metric_hsi_v4_candidate_active_l2_median,metric_hsi_v4_candidate_improvement_rate,metric_hsi_v4_candidate_ray_sign_acc,metric_hsi_v4_geometry_eligibility_coverage,metric_hsi_v4_candidate_tangent_l1_delta",
    "allowed_trainable_prefixes": [
      "hsi_translation_refine_v4_head.correction_trunk.",
      "hsi_translation_refine_v4_head.correction_head."
    ],
    "required_trainable_prefixes": [
      "hsi_translation_refine_v4_head.correction_trunk.",
      "hsi_translation_refine_v4_head.correction_head."
    ],
    "required_gradient_prefixes": [
      "hsi_translation_refine_v4_head.correction_trunk.",
      "hsi_translation_refine_v4_head.correction_head."
    ],
    "val_interval": 1,
    "max_steps_per_epoch": 1000,
    "max_val_steps": 3
  },
  "training_prior": {
    "center_noise": 0.0,
    "size_noise": 0.0,
    "drop_prob": 0.0,
    "smpl_perturb_mode": "translation",
    "smpl_translation_noise_contract": "v4_deterministic",
    "smpl_v4_noise_seed": 42,
    "smpl_v4_validation_epoch": 0,
    "smpl_gt_override_prob": 0.0
  },
  "loss": {
    "type": "hungarian",
    "pose_weight": 0.0,
    "betas_weight": 0.0,
    "transl_cam_weight": 0.0,
    "conf_weight": 0.0,
    "bbox_weight": 0.0,
    "giou_weight": 0.0,
    "joints3d_weight": 0.0,
    "projected_joints2d_weight": 0.0,
    "projected_bbox_weight": 0.0,
    "projected_giou_weight": 0.0,
    "use_vggt_camera_projection": true,
    "projection_camera_source": "gt",
    "hsi_pose_weight": 0.0,
    "hsi_betas_weight": 0.0,
    "hsi_transl_cam_weight": 0.0,
    "hsi_ray_delta_weight": 0.0,
    "hsi_tangent_delta_weight": 0.0,
    "hsi_joints3d_weight": 0.0,
    "hsi_vertices_weight": 0.0,
    "hsi_projected_joints2d_weight": 0.0,
    "hsi_align_point_weight": 0.0,
    "hsi_align_delta_reg_weight": 0.0,
    "hsi_align_no_worse_weight": 0.0,
    "hsi_transl_clean_identity_weight": 0.0,
    "hsi_transl_noise_gate_weight": 0.0,
    "hsi_delta_reg_weight": 0.0,
    "hsi_no_worse_weight": 0.0,
    "hsi_gate_reg_weight": 0.0,
    "hsi_depth_teacher_weight": 0.0,
    "hsi_smpl_scale_teacher_weight": 0.0,
    "hsi_anchor_depth_weight": 0.0,
    "hsi_anchor_scene_xyz_weight": 0.0,
    "hsi_contact_weight": 0.0,
    "hsi_v4_candidate_transl_weight": 8.0,
    "hsi_v4_candidate_ray_weight": 4.0,
    "hsi_v4_candidate_tangent_weight": 4.0,
    "hsi_v4_candidate_reg_weight": 0.01,
    "hsi_v4_active_threshold_m": 0.05,
    "id_weight": 0.0
  },
  "matching": {
    "enabled": true,
    "cost_conf": 0.5,
    "cost_bbox": 8.0,
    "cost_giou": 4.0,
    "cost_kpts": 0.0
  }
}