{
  "image": "/home/zhw/xyb_space/bedlam/processed_bedlam/Training/20221013_3_250_batch01hand_orbit_bigOffice_seq_000000/rgb/seq_000000_0010.png",
  "checkpoint": "/home/zhw/lab_users/xyb/home/projects/vggt-human/outputs/train/smpl_dab_roi_pool_3d_refine_20q/checkpoint_latest.pt",
  "use_gt_box_prior": true,
  "gt_box_prior_center_noise": 0.05,
  "gt_box_prior_size_noise": 0.1,
  "gt_box_prior_drop_prob": 0.03,
  "ply_files": [
    "/home/zhw/lab_users/xyb/home/projects/vggt-human/outputs/vis/smpl_dab_roi_pool_3d_refine_20q_noisy_prior_c005_s010/seq_000000_0010_pred_mesh_top03.ply",
    "/home/zhw/lab_users/xyb/home/projects/vggt-human/outputs/vis/smpl_dab_roi_pool_3d_refine_20q_noisy_prior_c005_s010/seq_000000_0010_gt_mesh_top03.ply",
    "/home/zhw/lab_users/xyb/home/projects/vggt-human/outputs/vis/smpl_dab_roi_pool_3d_refine_20q_noisy_prior_c005_s010/seq_000000_0010_pred_gt_mesh_top03.ply",
    "/home/zhw/lab_users/xyb/home/projects/vggt-human/outputs/vis/smpl_dab_roi_pool_3d_refine_20q_noisy_prior_c005_s010/seq_000000_0010_vggt_depth_mesh.ply",
    "/home/zhw/lab_users/xyb/home/projects/vggt-human/outputs/vis/smpl_dab_roi_pool_3d_refine_20q_noisy_prior_c005_s010/seq_000000_0010_scene_vggt_points_smpl_mesh.ply"
  ],
  "predictions": [
    {
      "rank": 0,
      "query_index": 2,
      "confidence": 0.9571616649627686,
      "bbox_cxcywh_norm": [
        0.45194992423057556,
        0.501787543296814,
        0.15235967934131622,
        0.9998956918716431
      ],
      "bbox_xyxy_pixels": [
        480.98570823669434,
        1.3245820999145508,
        676.0060977935791,
        721.2494802474976
      ],
      "pred_transl_cam": [
        -0.16254755854606628,
        0.4317122995853424,
        2.0476386547088623
      ],
      "projected_joints_2d": [
        [
          548.776611328125,
          441.5143737792969
        ],
        [
          549.2578125,
          470.8042297363281
        ],
        [
          551.77978515625,
          490.05914306640625
        ],
        [
          525.3165283203125,
          394.61590576171875
        ],
        [
          563.1453857421875,
          602.9588623046875
        ],
        [
          551.673828125,
          663.8331298828125
        ],
        [
          535.1813354492188,
          326.8967590332031
        ],
        [
          542.5921630859375,
          745.064453125
        ],
        [
          498.6315002441406,
          801.0327758789062
        ],
        [
          541.808837890625,
          299.38323974609375
        ],
        [
          593.9420776367188,
          751.4985961914062
        ],
        [
          556.5254516601562,
          840.0745239257812
        ],
        [
          530.3253173828125,
          196.2269744873047
        ],
        [
          534.6444702148438,
          240.4980926513672
        ],
        [
          523.1956176757812,
          243.19674682617188
        ],
        [
          568.9627685546875,
          170.20042419433594
        ],
        [
          556.3656005859375,
          215.03594970703125
        ],
        [
          552.1119995117188,
          219.83395385742188
        ],
        [
          658.9652709960938,
          152.7962646484375
        ],
        [
          689.363037109375,
          154.22930908203125
        ],
        [
          654.2630615234375,
          47.70562744140625
        ],
        [
          683.6549682617188,
          17.610214233398438
        ],
        [
          640.8834838867188,
          7.4600348472595215
        ],
        [
          682.956298828125,
          -34.04014205932617
        ],
        [
          628.9413452148438,
          142.5636444091797
        ],
        [
          605.0318603515625,
          128.28350830078125
        ],
        [
          603.9984130859375,
          122.35340118408203
        ],
        [
          549.3064575195312,
          145.66952514648438
        ],
        [
          551.3956298828125,
          131.95587158203125
        ],
        [
          630.6027221679688,
          747.4566650390625
        ],
        [
          599.205810546875,
          739.7593994140625
        ],
        [
          511.828369140625,
          758.7599487304688
        ],
        [
          600.0612182617188,
          839.2247924804688
        ],
        [
          560.118896484375,
          860.0748291015625
        ],
        [
          469.6045227050781,
          811.8997192382812
        ],
        [
          628.4558715820312,
          -5.894525527954102
        ],
        [
          615.983642578125,
          -39.48566818237305
        ],
        [
          615.1412353515625,
          -42.375579833984375
        ],
        [
          622.5560302734375,
          -34.04913330078125
        ],
        [
          636.8257446289062,
          -19.31947898864746
        ],
        [
          632.2122192382812,
          -35.61152267456055
        ],
        [
          657.058837890625,
          -89.24359893798828
        ],
        [
          672.417236328125,
          -98.0885238647461
        ],
        [
          690.6875610351562,
          -91.26177215576172
        ],
        [
          712.63037109375,
          -72.25381469726562
        ]
      ],
      "projected_joints_mask": [
        true,
        true,
        true,
        true,
        true,
        true,
        true,
        false,
        false,
        true,
        false,
        false,
        true,
        true,
        true,
        true,
        true,
        true,
        true,
        true,
        true,
        true,
        true,
        false,
        true,
        true,
        true,
        true,
        true,
        false,
        false,
        false,
        false,
        false,
        false,
        false,
        false,
        false,
        false,
        false,
        false,
        false,
        false,
        false,
        false
      ],
      "vggt_intrinsics_input": [
        [
          461.2658996582031,
          0.0,
          259.0
        ],
        [
          0.0,
          648.2590942382812,
          259.0
        ],
        [
          0.0,
          0.0,
          1.0
        ]
      ],
      "vggt_input_size": 518,
      "vggt_camera_from_world": [
        [
          0.999995768070221,
          -0.0011435598134994507,
          0.002668835921213031,
          0.0001674499362707138
        ],
        [
          0.0011416285997256637,
          0.9999991059303284,
          0.0007250545895658433,
          -0.00013046525418758392
        ],
        [
          -0.0026696629356592894,
          -0.0007220046827569604,
          0.9999961853027344,
          -0.0001383461058139801
        ]
      ],
      "gt_projected_joints_2d": [
        [
          537.0225830078125,
          436.3343200683594
        ],
        [
          544.7039184570312,
          465.0292053222656
        ],
        [
          536.1182250976562,
          483.04156494140625
        ],
        [
          512.5001220703125,
          390.93585205078125
        ],
        [
          575.4857177734375,
          587.5809326171875
        ],
        [
          526.8563232421875,
          648.555419921875
        ],
        [
          531.1167602539062,
          327.6197814941406
        ],
        [
          553.4242553710938,
          723.0446166992188
        ],
        [
          477.4553527832031,
          780.386962890625
        ],
        [
          534.7696533203125,
          301.03314208984375
        ],
        [
          609.0415649414062,
          736.7190551757812
        ],
        [
          526.8558959960938,
          818.9583740234375
        ],
        [
          513.0310668945312,
          202.7707061767578
        ],
        [
          526.994384765625,
          243.2908477783203
        ],
        [
          506.36376953125,
          249.7792510986328
        ],
        [
          545.8128051757812,
          174.9284210205078
        ],
        [
          550.2413940429688,
          220.4165802001953
        ],
        [
          522.2008056640625,
          224.42344665527344
        ],
        [
          645.0989379882812,
          154.90679931640625
        ],
        [
          614.7874145507812,
          147.83493041992188
        ],
        [
          635.0404663085938,
          46.38050079345703
        ],
        [
          654.9871826171875,
          -2.9341554641723633
        ],
        [
          616.8121948242188,
          22.49785804748535
        ],
        [
          654.89208984375,
          -51.37834548950195
        ],
        [
          597.2158203125,
          143.41787719726562
        ],
        [
          566.8837280273438,
          132.70391845703125
        ],
        [
          573.30126953125,
          125.09912872314453
        ],
        [
          512.4524536132812,
          155.36094665527344
        ],
        [
          530.1463623046875,
          138.2262420654297
        ],
        [
          643.4481201171875,
          736.7821655273438
        ],
        [
          618.6618041992188,
          727.1983642578125
        ],
        [
          525.5110473632812,
          734.8396606445312
        ],
        [
          569.8258056640625,
          819.8389892578125
        ],
        [
          526.7059936523438,
          837.45263671875
        ],
        [
          454.1167907714844,
          791.3307495117188
        ],
        [
          589.778076171875,
          -7.309471130371094
        ],
        [
          581.540771484375,
          -13.129764556884766
        ],
        [
          584.9247436523438,
          -8.020231246948242
        ],
        [
          596.2593383789062,
          1.359802007675171
        ],
        [
          614.4310302734375,
          13.679462432861328
        ],
        [
          625.2492065429688,
          -84.08795166015625
        ],
        [
          635.7294311523438,
          -118.14374542236328
        ],
        [
          644.104248046875,
          -117.1997299194336
        ],
        [
          659.2911987304688,
          -102.45319366455078
        ],
        [
          678.0972290039062,
          -76.10271453857422
        ]
      ],
      "gt_projected_joints_mask": [
        true,
        true,
        true,
        true,
        true,
        true,
        true,
        false,
        false,
        true,
        false,
        false,
        true,
        true,
        true,
        true,
        true,
        true,
        true,
        true,
        true,
        false,
        true,
        false,
        true,
        true,
        true,
        true,
        true,
        false,
        false,
        false,
        false,
        false,
        false,
        false,
        false,
        false,
        true,
        true,
        false,
        false,
        false,
        false,
        false
      ]
    },
    {
      "rank": 1,
      "query_index": 1,
      "confidence": 0.9528068900108337,
      "bbox_cxcywh_norm": [
        0.1337997019290924,
        0.644543468952179,
        0.15194065868854523,
        0.4680913984775543
      ],
      "bbox_xyxy_pixels": [
        74.02159690856934,
        295.5583941936493,
        268.5056400299072,
        632.5842010974884
      ],
      "pred_transl_cam": [
        -1.3226274251937866,
        0.16906467080116272,
        3.181302309036255
      ],
      "projected_joints_2d": [
        [
          167.77249145507812,
          347.6871032714844
        ],
        [
          201.4859161376953,
          360.14215087890625
        ],
        [
          156.37875366210938,
          361.6526184082031
        ],
        [
          156.02146911621094,
          325.3149108886719
        ],
        [
          225.78392028808594,
          469.5499267578125
        ],
        [
          142.2429656982422,
          473.2109069824219
        ],
        [
          140.53250122070312,
          343.3307189941406
        ],
        [
          254.5949249267578,
          582.4637451171875
        ],
        [
          150.06439208984375,
          573.5776977539062
        ],
        [
          136.4720458984375,
          355.1277770996094
        ],
        [
          263.8587341308594,
          616.5645141601562
        ],
        [
          120.59188842773438,
          604.7948608398438
        ],
        [
          95.30541229248047,
          374.0234375
        ],
        [
          142.6725311279297,
          360.5071105957031
        ],
        [
          84.30953979492188,
          361.57257080078125
        ],
        [
          100.0403823852539,
          396.543701171875
        ],
        [
          168.70263671875,
          381.612060546875
        ],
        [
          69.17798614501953,
          383.8904724121094
        ],
        [
          218.2271728515625,
          442.10345458984375
        ],
        [
          60.585182189941406,
          433.8622131347656
        ],
        [
          169.4644317626953,
          507.2813415527344
        ],
        [
          100.22261047363281,
          505.5920104980469
        ],
        [
          165.4717254638672,
          532.4910278320312
        ],
        [
          103.40088653564453,
          530.2534790039062
        ],
        [
          94.15049743652344,
          430.9365539550781
        ],
        [
          70.1009750366211,
          421.8507995605469
        ],
        [
          99.4024429321289,
          418.83673095703125
        ],
        [
          52.29273223876953,
          391.8814697265625
        ],
        [
          115.29873657226562,
          386.38330078125
        ],
        [
          244.5137481689453,
          626.6630249023438
        ],
        [
          273.5556640625,
          620.6867065429688
        ],
        [
          263.20166015625,
          581.9864501953125
        ],
        [
          117.62351989746094,
          621.2518920898438
        ],
        [
          106.77100372314453,
          611.7080688476562
        ],
        [
          162.70664978027344,
          573.1356201171875
        ],
        [
          130.4657745361328,
          538.5888061523438
        ],
        [
          139.63768005371094,
          561.7666625976562
        ],
        [
          149.7803192138672,
          566.0999145507812
        ],
        [
          162.04847717285156,
          561.6080932617188
        ],
        [
          176.61660766601562,
          552.5497436523438
        ],
        [
          139.43988037109375,
          528.8363647460938
        ],
        [
          119.1541976928711,
          556.06884765625
        ],
        [
          107.82290649414062,
          561.5404052734375
        ],
        [
          99.27662658691406,
          558.7719116210938
        ],
        [
          90.00697326660156,
          551.0405883789062
        ]
      ],
      "projected_joints_mask": [
        true,
        true,
        true,
        true,
        true,
        true,
        true,
        true,
        true,
        true,
        true,
        true,
        true,
        true,
        true,
        true,
        true,
        true,
        true,
        true,
        true,
        true,
        true,
        true,
        true,
        true,
        true,
        true,
        true,
        true,
        true,
        true,
        true,
        true,
        true,
        true,
        true,
        true,
        true,
        true,
        true,
        true,
        true,
        true,
        true
      ],
      "vggt_intrinsics_input": [
        [
          461.2658996582031,
          0.0,
          259.0
        ],
        [
          0.0,
          648.2590942382812,
          259.0
        ],
        [
          0.0,
          0.0,
          1.0
        ]
      ],
      "vggt_input_size": 518,
      "vggt_camera_from_world": [
        [
          0.999995768070221,
          -0.0011435598134994507,
          0.002668835921213031,
          0.0001674499362707138
        ],
        [
          0.0011416285997256637,
          0.9999991059303284,
          0.0007250545895658433,
          -0.00013046525418758392
        ],
        [
          -0.0026696629356592894,
          -0.0007220046827569604,
          0.9999961853027344,
          -0.0001383461058139801
        ]
      ],
      "gt_projected_joints_2d": [
        [
          140.0205078125,
          341.29864501953125
        ],
        [
          171.9432830810547,
          352.5330505371094
        ],
        [
          123.90575408935547,
          349.886474609375
        ],
        [
          132.23330688476562,
          321.9162292480469
        ],
        [
          194.90139770507812,
          463.5023193359375
        ],
        [
          107.83975982666016,
          460.4611511230469
        ],
        [
          121.23687744140625,
          346.0564270019531
        ],
        [
          204.79541015625,
          580.626220703125
        ],
        [
          99.31874084472656,
          573.6943359375
        ],
        [
          116.67398834228516,
          359.59442138671875
        ],
        [
          207.0209197998047,
          612.4887084960938
        ],
        [
          64.7900161743164,
          601.2097778320312
        ],
        [
          74.34423065185547,
          380.0611572265625
        ],
        [
          124.87258911132812,
          371.0385437011719
        ],
        [
          63.79686737060547,
          361.60577392578125
        ],
        [
          70.70497131347656,
          403.25811767578125
        ],
        [
          146.9516143798828,
          395.1297302246094
        ],
        [
          40.352088928222656,
          380.6612854003906
        ],
        [
          167.50021362304688,
          450.0835266113281
        ],
        [
          25.446163177490234,
          410.4234619140625
        ],
        [
          105.67967224121094,
          510.5398254394531
        ],
        [
          26.358325958251953,
          489.4630432128906
        ],
        [
          97.62548065185547,
          532.6034545898438
        ],
        [
          19.310033798217773,
          513.3782348632812
        ],
        [
          42.6324577331543,
          432.5705871582031
        ],
        [
          23.47931480407715,
          415.98089599609375
        ],
        [
          51.27062225341797,
          418.5813293457031
        ],
        [
          25.995677947998047,
          384.9271545410156
        ],
        [
          85.33274841308594,
          391.7469177246094
        ],
        [
          186.08819580078125,
          618.4461669921875
        ],
        [
          216.34693908691406,
          615.4182739257812
        ],
        [
          212.18545532226562,
          584.138671875
        ],
        [
          60.280975341796875,
          611.57470703125
        ],
        [
          48.10708999633789,
          608.6015014648438
        ],
        [
          110.74071502685547,
          577.9949340820312
        ],
        [
          56.23649978637695,
          538.49658203125
        ],
        [
          70.63170623779297,
          561.7990112304688
        ],
        [
          83.14531707763672,
          565.397216796875
        ],
        [
          95.09463500976562,
          559.7555541992188
        ],
        [
          106.44195556640625,
          548.5977783203125
        ],
        [
          47.76808166503906,
          526.140380859375
        ],
        [
          19.381559371948242,
          545.0049438476562
        ],
        [
          8.575425148010254,
          545.449951171875
        ],
        [
          4.332770347595215,
          538.2776489257812
        ],
        [
          2.233877182006836,
          525.9441528320312
        ]
      ],
      "gt_projected_joints_mask": [
        true,
        true,
        true,
        true,
        true,
        true,
        true,
        true,
        true,
        true,
        true,
        true,
        true,
        true,
        true,
        true,
        true,
        true,
        true,
        true,
        true,
        true,
        true,
        true,
        true,
        true,
        true,
        true,
        true,
        true,
        true,
        true,
        true,
        true,
        true,
        true,
        true,
        true,
        true,
        true,
        true,
        true,
        true,
        true,
        true
      ]
    },
    {
      "rank": 2,
      "query_index": 0,
      "confidence": 0.9407064914703369,
      "bbox_cxcywh_norm": [
        0.6550674438476562,
        0.5113516449928284,
        0.12462668120861053,
        0.5685798525810242
      ],
      "bbox_xyxy_pixels": [
        758.7252521514893,
        163.48443746566772,
        918.2474040985107,
        572.8619313240051
      ],
      "pred_transl_cam": [
        0.7526518702507019,
        0.08864568918943405,
        3.616389274597168
      ],
      "projected_joints_2d": [
        [
          875.4256591796875,
          330.457275390625
        ],
        [
          893.2621459960938,
          351.8698425292969
        ],
        [
          852.9391479492188,
          350.1669006347656
        ],
        [
          876.875244140625,
          305.0271301269531
        ],
        [
          906.3925170898438,
          444.42132568359375
        ],
        [
          820.82421875,
          441.9651794433594
        ],
        [
          880.1756591796875,
          276.7886047363281
        ],
        [
          885.4320068359375,
          520.5042114257812
        ],
        [
          816.8805541992188,
          531.7277221679688
        ],
        [
          881.4382934570312,
          271.3984375
        ],
        [
          908.523193359375,
          544.2882080078125
        ],
        [
          796.6729736328125,
          552.7659301757812
        ],
        [
          876.3705444335938,
          221.65972900390625
        ],
        [
          902.2719116210938,
          239.54225158691406
        ],
        [
          854.2054443359375,
          244.83489990234375
        ],
        [
          885.0472412109375,
          221.99232482910156
        ],
        [
          930.8150024414062,
          243.45504760742188
        ],
        [
          830.5640258789062,
          255.31326293945312
        ],
        [
          957.9795532226562,
          308.3726806640625
        ],
        [
          815.5560302734375,
          318.4464416503906
        ],
        [
          963.797119140625,
          345.84796142578125
        ],
        [
          825.5960693359375,
          341.4853515625
        ],
        [
          973.0931396484375,
          362.2354431152344
        ],
        [
          829.8909912109375,
          355.7367858886719
        ],
        [
          885.318115234375,
          221.48875427246094
        ],
        [
          872.7645263671875,
          208.75442504882812
        ],
        [
          896.8106689453125,
          207.39854431152344
        ],
        [
          859.0062255859375,
          203.5884552001953
        ],
        [
          908.0729370117188,
          201.73733520507812
        ],
        [
          912.948486328125,
          551.9505615234375
        ],
        [
          922.4988403320312,
          545.5853881835938
        ],
        [
          877.8080444335938,
          520.8304443359375
        ],
        [
          799.1971435546875,
          561.3695068359375
        ],
        [
          784.34814453125,
          556.5944213867188
        ],
        [
          821.43017578125,
          535.5252685546875
        ],
        [
          941.8965454101562,
          373.07818603515625
        ],
        [
          967.0799560546875,
          381.2016906738281
        ],
        [
          980.234619140625,
          380.88653564453125
        ],
        [
          988.4244384765625,
          376.7874755859375
        ],
        [
          994.1500244140625,
          371.47650146484375
        ],
        [
          864.4987182617188,
          352.0963134765625
        ],
        [
          849.0843505859375,
          366.2220764160156
        ],
        [
          837.7181396484375,
          370.56103515625
        ],
        [
          827.5300903320312,
          371.3354187011719
        ],
        [
          815.877685546875,
          370.297119140625
        ]
      ],
      "projected_joints_mask": [
        true,
        true,
        true,
        true,
        true,
        true,
        true,
        true,
        true,
        true,
        true,
        true,
        true,
        true,
        true,
        true,
        true,
        true,
        true,
        true,
        true,
        true,
        true,
        true,
        true,
        true,
        true,
        true,
        true,
        true,
        true,
        true,
        true,
        true,
        true,
        true,
        true,
        true,
        true,
        true,
        true,
        true,
        true,
        true,
        true
      ],
      "vggt_intrinsics_input": [
        [
          461.2658996582031,
          0.0,
          259.0
        ],
        [
          0.0,
          648.2590942382812,
          259.0
        ],
        [
          0.0,
          0.0,
          1.0
        ]
      ],
      "vggt_input_size": 518,
      "vggt_camera_from_world": [
        [
          0.999995768070221,
          -0.0011435598134994507,
          0.002668835921213031,
          0.0001674499362707138
        ],
        [
          0.0011416285997256637,
          0.9999991059303284,
          0.0007250545895658433,
          -0.00013046525418758392
        ],
        [
          -0.0026696629356592894,
          -0.0007220046827569604,
          0.9999961853027344,
          -0.0001383461058139801
        ]
      ],
      "gt_projected_joints_2d": [
        [
          857.4961547851562,
          334.9620666503906
        ],
        [
          876.5051879882812,
          356.933837890625
        ],
        [
          836.7182006835938,
          356.69512939453125
        ],
        [
          856.2892456054688,
          309.41888427734375
        ],
        [
          898.706298828125,
          448.7489013671875
        ],
        [
          804.7532348632812,
          448.91815185546875
        ],
        [
          858.749755859375,
          278.2698669433594
        ],
        [
          874.0299682617188,
          526.5512084960938
        ],
        [
          801.680419921875,
          531.4667358398438
        ],
        [
          860.7153930664062,
          275.7712707519531
        ],
        [
          897.2352294921875,
          549.5557250976562
        ],
        [
          782.820556640625,
          551.7017211914062
        ],
        [
          861.1017456054688,
          232.88699340820312
        ],
        [
          885.1454467773438,
          249.22084045410156
        ],
        [
          836.938232421875,
          250.3597869873047
        ],
        [
          868.208984375,
          241.43447875976562
        ],
        [
          910.6436767578125,
          258.93701171875
        ],
        [
          812.252685546875,
          261.8377380371094
        ],
        [
          940.8648681640625,
          321.67071533203125
        ],
        [
          791.7977294921875,
          323.16265869140625
        ],
        [
          941.0076904296875,
          358.6852722167969
        ],
        [
          806.1760864257812,
          356.92681884765625
        ],
        [
          944.2288818359375,
          377.041748046875
        ],
        [
          804.0963134765625,
          373.2958984375
        ],
        [
          868.3729858398438,
          251.83901977539062
        ],
        [
          858.2266235351562,
          237.62388610839844
        ],
        [
          881.953369140625,
          238.6189727783203
        ],
        [
          845.4237670898438,
          222.49331665039062
        ],
        [
          894.2752075195312,
          225.3931884765625
        ],
        [
          901.6571655273438,
          555.4334716796875
        ],
        [
          911.1038818359375,
          551.3042602539062
        ],
        [
          866.3992919921875,
          527.94189453125
        ],
        [
          786.7827758789062,
          560.1293334960938
        ],
        [
          770.67919921875,
          555.0851440429688
        ],
        [
          804.3992309570312,
          535.0013427734375
        ],
        [
          910.244384765625,
          383.3646545410156
        ],
        [
          930.0921020507812,
          396.3495178222656
        ],
        [
          942.9251098632812,
          398.27728271484375
        ],
        [
          953.1382446289062,
          395.0125427246094
        ],
        [
          961.9176635742188,
          389.9276428222656
        ],
        [
          828.3421020507812,
          388.3528137207031
        ],
        [
          816.5933227539062,
          395.5569763183594
        ],
        [
          806.947509765625,
          393.5503234863281
        ],
        [
          798.2890625,
          388.20245361328125
        ],
        [
          787.56201171875,
          379.04400634765625
        ]
      ],
      "gt_projected_joints_mask": [
        true,
        true,
        true,
        true,
        true,
        true,
        true,
        true,
        true,
        true,
        true,
        true,
        true,
        true,
        true,
        true,
        true,
        true,
        true,
        true,
        true,
        true,
        true,
        true,
        true,
        true,
        true,
        true,
        true,
        true,
        true,
        true,
        true,
        true,
        true,
        true,
        true,
        true,
        true,
        true,
        true,
        true,
        true,
        true,
        true
      ]
    }
  ]
}